dataclass_to_diagram/__init__.py
dataclass_to_diagram/__main__.py
dataclass_to_diagram/converters/__init__.py
dataclass_to_diagram/converters/base_converter.py
dataclass_to_diagram/converters/converters_params.py
dataclass_to_diagram/converters/dbml.py
dataclass_to_diagram/converters/kroki_c4_puml.py
dataclass_to_diagram/converters/kroki_request.py
dataclass_to_diagram/dia/__init__.py
dataclass_to_diagram/dia/base.py
dataclass_to_diagram/dia/mermaid_er/__init__.py
dataclass_to_diagram/dia/mermaid_er/main.py
dataclass_to_diagram/dia/mermaid_state/mermaid_state.py
dataclass_to_diagram/dia/nwdiag.py
dataclass_to_diagram/exceptions.py
dataclass_to_diagram/exporters/__init__.py
dataclass_to_diagram/exporters/base_exporter.py
dataclass_to_diagram/exporters/c4_to_plantuml/__init__.py
dataclass_to_diagram/exporters/c4_to_plantuml/args_dict_to_str.py
dataclass_to_diagram/exporters/c4_to_plantuml/base_element_to_puml.py
dataclass_to_diagram/exporters/c4_to_plantuml/c4_to_puml.py
dataclass_to_diagram/exporters/c4_to_plantuml/component_to_puml.py
dataclass_to_diagram/exporters/c4_to_plantuml/container_to_puml.py
dataclass_to_diagram/exporters/c4_to_plantuml/context_to_puml.py
dataclass_to_diagram/exporters/c4_to_plantuml/exporter.py
dataclass_to_diagram/exporters/c4_to_plantuml/rel_to_puml.py
dataclass_to_diagram/exporters/c4_to_plantuml/sprites_to_puml.py
dataclass_to_diagram/exporters/c4_to_plantuml/tag_to_puml.py
dataclass_to_diagram/exporters/erd_to_dbml/__init__.py
dataclass_to_diagram/exporters/erd_to_dbml/column.py
dataclass_to_diagram/exporters/erd_to_dbml/database.py
dataclass_to_diagram/exporters/erd_to_dbml/enum.py
dataclass_to_diagram/exporters/erd_to_dbml/exporter.py
dataclass_to_diagram/exporters/erd_to_dbml/note.py
dataclass_to_diagram/exporters/erd_to_dbml/project_definition.py
dataclass_to_diagram/exporters/erd_to_dbml/relation.py
dataclass_to_diagram/exporters/erd_to_dbml/table.py
dataclass_to_diagram/exporters/erd_to_dbml/table_group.py
dataclass_to_diagram-0.0.5.dist-info/METADATA
dataclass_to_diagram-0.0.5.dist-info/WHEEL
dataclass_to_diagram-0.0.5.dist-info/entry_points.txt
dataclass_to_diagram-0.0.5.dist-info/RECORD
