Metadata-Version: 2.1
Name: dataclass-to-diagram
Version: 0.0.5
Summary: Создание диаграмм из датаклассов python
Home-page: https://github.com/Konstantin-Dudersky/dataclass_to_diagram.git
Author: konstantin-dudersky
Author-email: konstantin.dudersky@gmail.com
Requires-Python: >=3.11,<4.0
Classifier: Programming Language :: Python :: 3
Classifier: Programming Language :: Python :: 3.11
Requires-Dist: httpx
Requires-Dist: requests
Requires-Dist: typer[all] (>=0.7.0,<0.8.0)
Requires-Dist: typing_extensions
Project-URL: Repository, https://github.com/Konstantin-Dudersky/dataclass_to_diagram.git
